userdefaults3.py
userdefaults3-1.1.8.dist-info/LICENSE
userdefaults3-1.1.8.dist-info/WHEEL
userdefaults3-1.1.8.dist-info/METADATA
userdefaults3-1.1.8.dist-info/RECORD
