Metadata-Version: 2.1
Name: userdefaults3
Version: 1.1.8
Summary: Python 3 rewrite of userdefaults, a pure-Python interface to NSUserDefaults.
Home-page: https://github.com/ongyx/tankobon
Author: Ong Yong Xin
Author-email: ongyongxin2020+github@gmail.com
Requires-Python: >=3.6
Classifier: Programming Language :: Python :: 3
Classifier: License :: OSI Approved :: MIT License
Classifier: Operating System :: OS Independent
Requires-Dist: rubicon-objc
